beelzebub/md_iso/__init__.py
beelzebub/md_iso/__main__.py
beelzebub/md_iso/templates/iso19115-2.xml.j2
beelzebub_md_iso-0.2.0.dist-info/entry_points.txt
beelzebub_md_iso-0.2.0.dist-info/LICENSE
beelzebub_md_iso-0.2.0.dist-info/WHEEL
beelzebub_md_iso-0.2.0.dist-info/METADATA
beelzebub_md_iso-0.2.0.dist-info/RECORD
