Metadata-Version: 2.1
Name: beelzebub-md-iso
Version: 0.2.0
Summary: Translate between mdJson and ISO19115-2
Home-page: https://github.com/paul-breen/beelzebub-md-iso
License: Apache-2.0
Author: Paul Breen
Author-email: paul.breen6@btinternet.com
Requires-Python: >=3.8,<4.0
Classifier: License :: OSI Approved :: Apache Software License
Classifier: Programming Language :: Python :: 3
Classifier: Programming Language :: Python :: 3.8
Classifier: Programming Language :: Python :: 3.9
Classifier: Programming Language :: Python :: 3.10
Classifier: Programming Language :: Python :: 3.11
Requires-Dist: beelzebub (>=1.0.0,<2.0.0)
Project-URL: Documentation, https://github.com/paul-breen/beelzebub-md-iso/blob/main/README.md
Project-URL: Repository, https://github.com/paul-breen/beelzebub-md-iso
